{"media":[{"who":{"creator":[{"username":"vUVPsTvAuXVpdrPsD90pDOIZd"}]},"when":{"start_time":"2016-03-08T16:49:17.000Z","end_time":"2016-03-08T18:12:37.000Z"},"why":[{"intent_used_synonym":"Love","intent_index_in_category":3,"intent_name":"Love","intent_category_name":"Popular","intent_category_id":"6eR629bBE0","intent_emoji_id":"wXfsoBnXnG","intent_emoji_unicode":"1f60d"}],"media_type":"photo","media_source":{"default_src":"https://d3j4aoik7k8ki7.cloudfront.net/28D13EF0-75CA-46AC-A778-D5D5F753CF43.jpg","mime_type":"jpg","raw":"https://d3j4aoik7k8ki7.cloudfront.net/28D13EF0-75CA-46AC-A778-D5D5F753CF43.jpg","full":"","large":"","medium":"","small":""},"representative_media_source":[{}],"caption":"Love, During Next Generation Search Systems, On Mar 8, 2016"},{"who":{"creator":[{"username":"vUVPsTvAuXVpdrPsD90pDOIZd"}]},"media_type":"audio","media_source":{"default_src":"https://d3j4aoik7k8ki7.cloudfront.net/48423A8B-1E7B-4B9F-A409-17462613304B.aif","mime_type":"aif"}}],"title":"Next Generation Search Systems","start_time":"2016-03-08T18:12:43.701Z","end_time":"2016-03-08T18:12:43.704Z","id":"ngxcHvvLw1"}